dwave_sdk/__init__.py
dwave_sdk/package_info.py
dwave_sdk/packages.py
dwave_sdk-0.2.0.dist-info/DESCRIPTION.rst
dwave_sdk-0.2.0.dist-info/METADATA
dwave_sdk-0.2.0.dist-info/RECORD
dwave_sdk-0.2.0.dist-info/WHEEL
dwave_sdk-0.2.0.dist-info/metadata.json
dwave_sdk-0.2.0.dist-info/top_level.txt
