Metadata-Version: 1.0
Name: dwave-sdk
Version: 0.2.0
Summary: Software development kit for open source D-Wave tools
Home-page: https://github.com/dwavesystems/dwave_sdk
Author: D-Wave Systems Inc.
Author-email: tools@dwavesys.com
License: Apache 2.0
Platform: UNKNOWN
